ost_photometry/__init__.py
ost_photometry/calibration_parameters.py
ost_photometry/checks.py
ost_photometry/style.py
ost_photometry/terminal_output.py
ost_photometry/utilities.py
ost_photometry/analyze/__init__.py
ost_photometry/analyze/analyze.py
ost_photometry/analyze/calibration.py
ost_photometry/analyze/calibration_data.py
ost_photometry/analyze/correlate.py
ost_photometry/analyze/plots.py
ost_photometry/analyze/utilities.py
ost_photometry/reduce/__init__.py
ost_photometry/reduce/plots.py
ost_photometry/reduce/redu.py
ost_photometry/reduce/registration.py
ost_photometry/reduce/utilities.py
ost_photometry-0.3.4.dist-info/METADATA
ost_photometry-0.3.4.dist-info/WHEEL
ost_photometry-0.3.4.dist-info/licenses/LICENSE
ost_photometry-0.3.4.dist-info/RECORD
