Metadata-Version: 2.4
Name: ost_photometry
Version: 0.3.4
Summary: Phtometry reduction and analysis package for the OST observatory
Project-URL: Homepage, https://github.com/OST-Observatory/ost_photometry_package
Project-URL: Bug Tracker, https://github.com/OST-Observatory/ost_photometry_package/issues
Author-email: Rainer Hainich <rhainich@astro.physik.uni-potsdam.de>
License-File: LICENSE
Classifier: License :: OSI Approved :: GNU General Public License v3 (GPLv3)
Classifier: Operating System :: OS Independent
Classifier: Programming Language :: Python :: 3
Requires-Python: >=3.10
Requires-Dist: astroalign>=2.4
Requires-Dist: astropy>=6.1
Requires-Dist: astroquery>=0.4
Requires-Dist: bottleneck
Requires-Dist: ccdproc>=2.4
Requires-Dist: matplotlib>=3.5
Requires-Dist: numpy>=2.2.0
Requires-Dist: pandas
Requires-Dist: path>=16.0
Requires-Dist: pathlib>=1.0
Requires-Dist: photutils>=2.0.2
Requires-Dist: regions>=0.6
Requires-Dist: scikit-image
Requires-Dist: scikit-learn>=1.1
Requires-Dist: scipy
Requires-Dist: tqdm
Requires-Dist: twirl>=0.1
